pypus/Octo.py
pypus/__init__.py
pypus/cli.py
pypus/shelf.py
pypus-1.5.2.dist-info/METADATA
pypus-1.5.2.dist-info/WHEEL
pypus-1.5.2.dist-info/entry_points.txt
pypus-1.5.2.dist-info/licenses/LICENSE
pypus-1.5.2.dist-info/RECORD
